flake8_strict.py
flake8_strict-0.2.1.dist-info/METADATA
flake8_strict-0.2.1.dist-info/RECORD
flake8_strict-0.2.1.dist-info/WHEEL
flake8_strict-0.2.1.dist-info/entry_points.txt
flake8_strict-0.2.1.dist-info/top_level.txt
