Metadata-Version: 2.1
Name: flake8-strict
Version: 0.2.1
Summary: Flake8 plugin that checks Python code against a set of opinionated style rules
Home-page: https://github.com/smarkets/flake8-strict
Author: Smarkets Limited
Author-email: support@smarkets.com
Maintainer: Smarkets Limited
Maintainer-email: support@smarkets.com
License: MIT
Keywords: flake8,plugin,strict,hanging indent,trailing comma,trailing commas
Platform: UNKNOWN
Classifier: Development Status :: 3 - Alpha
Classifier: Environment :: Console
Classifier: Framework :: Flake8
Classifier: Intended Audience :: Developers
Classifier: License :: OSI Approved :: MIT License
Classifier: Operating System :: OS Independent
Classifier: Programming Language :: Python :: 2
Classifier: Programming Language :: Python :: 3
Classifier: Programming Language :: Python
Classifier: Topic :: Software Development :: Libraries :: Python Modules
Classifier: Topic :: Software Development :: Quality Assurance
Requires-Dist: enum-compat
Requires-Dist: flake8
Requires-Dist: setuptools
Requires-Dist: black; python_version >= "3.6"
